newcord/__init__.py
newcord/context.py
newcord/controllers.py
newcord/helpers.py
newcord/main.py
newcord/templates/base/.gitignore
newcord/templates/base/README.md
newcord/templates/base/pm2.json
newcord/templates/base/tests/__init__.py
newcord/templates/extras/prefix/mongodb/beanie/bot.py
newcord/templates/extras/prefix/mongodb/beanie/cogs/Admin/__init__.py
newcord/templates/extras/prefix/mongodb/beanie/cogs/Events/__init__.py
newcord/templates/extras/prefix/mongodb/beanie/cogs/Events/errors.py
newcord/templates/extras/prefix/mongodb/beanie/cogs/Todo/__init__.py
newcord/templates/extras/prefix/mongodb/beanie/cogs/__init__.py
newcord/templates/extras/prefix/mongodb/beanie/core/__init__.py
newcord/templates/extras/prefix/mongodb/beanie/core/bot.py
newcord/templates/extras/prefix/mongodb/beanie/core/cog.py
newcord/templates/extras/prefix/mongodb/beanie/core/context.py
newcord/templates/extras/prefix/mongodb/beanie/core/models.py
newcord/templates/extras/prefix/mongodb/beanie/helpers/__init__.py
newcord/templates/extras/prefix/mongodb/beanie/helpers/checks/__init__.py
newcord/templates/extras/prefix/mongodb/beanie/helpers/checks/core.py
newcord/templates/extras/prefix/mongodb/beanie/helpers/config.py
newcord/templates/extras/prefix/mongodb/beanie/helpers/errors/__init__.py
newcord/templates/extras/prefix/mongodb/beanie/helpers/errors/checks.py
newcord/templates/extras/prefix/mongodb/beanie/views/__init__.py
newcord/templates/extras/prefix/mongodb/beanie/views/base.py
newcord-0.0.2.dist-info/METADATA
newcord-0.0.2.dist-info/WHEEL
newcord-0.0.2.dist-info/entry_points.txt
newcord-0.0.2.dist-info/RECORD
